LICENSE
vfmc_core-1.5.1.dist-info/METADATA
vfmc_core-1.5.1.dist-info/WHEEL
vfmc_core-1.5.1.dist-info/licenses/LICENSE
vfmc_core/__init__.py
vfmc_core/vfmc_core.cpython-39-darwin.so
vfmc_core-1.5.1.dist-info/RECORD
