Metadata-Version: 2.4
Name: vfmc_core
Version: 1.5.1
Classifier: Programming Language :: Python :: 3
Classifier: Programming Language :: Rust
License-File: LICENSE
Summary: Rust core implementation for VFMC
Author-email: Rodney Kinney <rodney.m.kinney@gmail.com>
Requires-Python: >=3.9
